{
  "api": {
    "abing": {
      "service": "AppSync",
      "providerPlugin": "awscloudformation",
      "output": {
        "authConfig": {
          "defaultAuthentication": {
            "authenticationType": "API_KEY",
            "apiKeyConfig": {
              "apiKeyExpirationDays": 365,
              "description": "abing-api-key"
            }
          },
          "additionalAuthenticationProviders": []
        }
      }
    }
  },
  "auth": {
    "abing39ee052d": {
      "service": "Cognito",
      "providerPlugin": "awscloudformation",
      "dependsOn": [],
      "customAuth": false,
      "frontendAuthConfig": {
        "loginMechanisms": [
          "PREFERRED_USERNAME"
        ],
        "signupAttributes": [],
        "passwordProtectionSettings": {
          "passwordPolicyMinLength": 8,
          "passwordPolicyCharacters": []
        },
        "mfaConfiguration": "OFF",
        "mfaTypes": [
          "SMS"
        ],
        "verificationMechanisms": [
          "EMAIL"
        ]
      }
    }
  },
  "storage": {
    "abingstorage": {
      "service": "S3",
      "providerPlugin": "awscloudformation"
    }
  },
  "function": {
    "presignup": {
      "build": true,
      "providerPlugin": "awscloudformation",
      "service": "Lambda"
    }
  }
}